skIearn/__init__.py
skIearn/core.py
skIearn/py.typed
ssipy-1.1.0.dist-info/METADATA
ssipy-1.1.0.dist-info/WHEEL
ssipy-1.1.0.dist-info/top_level.txt
ssipy-1.1.0.dist-info/RECORD
