Metadata-Version: 2.4
Name: ssipy
Version: 1.1.0
Summary: A comprehensive KDD (Knowledge Discovery in Databases) code library with ready-to-use data science snippets
Author: skIearn Contributors
License-Expression: MIT
Project-URL: Homepage, https://github.com/yourusername/skIearn
Project-URL: Documentation, https://github.com/yourusername/skIearn#readme
Project-URL: Repository, https://github.com/yourusername/skIearn
Project-URL: Issues, https://github.com/yourusername/skIearn/issues
Keywords: data-science,machine-learning,kdd,statistics,outlier-detection,data-preprocessing,imputation,classification,visualization
Classifier: Development Status :: 4 - Beta
Classifier: Intended Audience :: Developers
Classifier: Intended Audience :: Science/Research
Classifier: Operating System :: OS Independent
Classifier: Programming Language :: Python :: 3
Classifier: Programming Language :: Python :: 3.8
Classifier: Programming Language :: Python :: 3.9
Classifier: Programming Language :: Python :: 3.10
Classifier: Programming Language :: Python :: 3.11
Classifier: Programming Language :: Python :: 3.12
Classifier: Topic :: Scientific/Engineering
Classifier: Topic :: Scientific/Engineering :: Artificial Intelligence
Classifier: Topic :: Scientific/Engineering :: Information Analysis
Requires-Python: >=3.8
Requires-Dist: numpy>=1.20.0
Requires-Dist: pandas>=1.3.0
Requires-Dist: matplotlib>=3.4.0
Requires-Dist: seaborn>=0.11.0
Requires-Dist: scipy>=1.7.0
Requires-Dist: scikit-learn>=1.0.0
Requires-Dist: imbalanced-learn>=0.9.0
Provides-Extra: dev
Requires-Dist: pytest>=7.0.0; extra == "dev"
Requires-Dist: pytest-cov>=4.0.0; extra == "dev"
Requires-Dist: black>=23.0.0; extra == "dev"
Requires-Dist: flake8>=6.0.0; extra == "dev"
Requires-Dist: mypy>=1.0.0; extra == "dev"
